CHANGES.txt
CONTRIBUTORS.txt
README.txt
setup.cfg
setup.py
docs/INSTALL.txt
docs/LICENSE.GPL
docs/LICENSE.txt
plumi/__init__.py
plumi.locales.egg-info/PKG-INFO
plumi.locales.egg-info/SOURCES.txt
plumi.locales.egg-info/dependency_links.txt
plumi.locales.egg-info/entry_points.txt
plumi.locales.egg-info/namespace_packages.txt
plumi.locales.egg-info/not-zip-safe
plumi.locales.egg-info/paster_plugins.txt
plumi.locales.egg-info/requires.txt
plumi.locales.egg-info/top_level.txt
plumi/locales/README.txt
plumi/locales/__init__.py
plumi/locales/configure.zcml
plumi/locales/tests.py
plumi/locales/locales/plumi.pot
plumi/locales/locales/es/LC_MESSAGES/plumi.mo
plumi/locales/locales/es/LC_MESSAGES/plumi.po
plumi/locales/locales/id/LC_MESSAGES/plumi.mo
plumi/locales/locales/id/LC_MESSAGES/plumi.po
plumi/locales/locales/it/LC_MESSAGES/plumi.mo
plumi/locales/locales/it/LC_MESSAGES/plumi.po
plumi/locales/locales/ms/LC_MESSAGES/plumi.mo
plumi/locales/locales/ms/LC_MESSAGES/plumi.po
plumi/locales/locales/pt_BR/LC_MESSAGES/plumi.mo
plumi/locales/locales/pt_BR/LC_MESSAGES/plumi.po