Metadata-Version: 1.0
Name: plumi.locales
Version: 4.4
Summary: Locales for Plumi 4.x
Home-page: https://github.com/plumi/plumi.locales
Author: Andy Nicholson
Author-email: andy@infiniterecursion.com.au
License: GPL
Keywords: plone plumi translation locales internationalization i18n l10n
Platform: UNKNOWN
Classifier: Framework :: Plone
Classifier: Programming Language :: Python
Classifier: Topic :: Software Development :: Libraries :: Python Modules
